webviz_core_components/Backdrop.py
webviz_core_components/Dialog.py
webviz_core_components/EdsIcon.py
webviz_core_components/Menu.py
webviz_core_components/Overlay.py
webviz_core_components/ScrollArea.py
webviz_core_components/Select.py
webviz_core_components/SmartNodeSelector.py
webviz_core_components/ViewVisibilityContainer.py
webviz_core_components/WebvizContentManager.py
webviz_core_components/WebvizDialog.py
webviz_core_components/WebvizPluginLayoutColumn.py
webviz_core_components/WebvizPluginLayoutRow.py
webviz_core_components/WebvizPluginLoadingIndicator.py
webviz_core_components/WebvizPluginPlaceholder.py
webviz_core_components/WebvizPluginPlaceholderWrapper.py
webviz_core_components/WebvizPluginWrapper.py
webviz_core_components/WebvizPluginsWrapper.py
webviz_core_components/WebvizSettings.py
webviz_core_components/WebvizSettingsDrawer.py
webviz_core_components/WebvizSettingsGroup.py
webviz_core_components/WebvizView.py
webviz_core_components/WebvizViewElement.py
webviz_core_components/__init__.py
webviz_core_components/_imports_.py
webviz_core_components/metadata.json
webviz_core_components/package.json
webviz_core_components/webviz_core_components.css
webviz_core_components/webviz_core_components.min.js
webviz_core_components/wrapped_components/__init__.py
webviz_core_components/wrapped_components/_argument_modifier.py
webviz_core_components/wrapped_components/checklist.py
webviz_core_components/wrapped_components/collapsive_header.py
webviz_core_components/wrapped_components/dropdown.py
webviz_core_components/wrapped_components/flexbox.py
webviz_core_components/wrapped_components/flexcolumn.py
webviz_core_components/wrapped_components/frame.py
webviz_core_components/wrapped_components/graph.py
webviz_core_components/wrapped_components/header.py
webviz_core_components/wrapped_components/label.py
webviz_core_components/wrapped_components/labeled_container.py
webviz_core_components/wrapped_components/radioitems.py
webviz_core_components-0.8.2.dist-info/LICENSE
webviz_core_components-0.8.2.dist-info/LICENSE.chromedriver
webviz_core_components-0.8.2.dist-info/METADATA
webviz_core_components-0.8.2.dist-info/WHEEL
webviz_core_components-0.8.2.dist-info/top_level.txt
webviz_core_components-0.8.2.dist-info/RECORD
