Metadata-Version: 2.1
Name: webviz_core_components
Version: 0.8.2
Summary: Core components for webviz-config
Home-page: https://github.com/equinor/webviz-core-components
Author: Equinor <noreply@equinor.com>
License: MIT
Classifier: Programming Language :: Python :: 3
Classifier: Operating System :: OS Independent
Classifier: Natural Language :: English
Classifier: Environment :: Web Environment
Classifier: Framework :: Dash
Classifier: Framework :: Flask
Classifier: Topic :: Multimedia :: Graphics
Classifier: Topic :: Scientific/Engineering
Classifier: Topic :: Scientific/Engineering :: Visualization
Classifier: License :: OSI Approved :: MIT License
Requires-Python: ~=3.8
License-File: LICENSE
License-File: LICENSE.chromedriver
Requires-Dist: dash>=2.0
Provides-Extra: dependencies
Requires-Dist: dash>=2.0; extra == "dependencies"
Provides-Extra: tests
Requires-Dist: bandit; extra == "tests"
Requires-Dist: black<24,>=22.12; extra == "tests"
Requires-Dist: dash[testing]; extra == "tests"
Requires-Dist: flask<2.3; extra == "tests"
Requires-Dist: pylint; extra == "tests"
Requires-Dist: selenium<=4.2.0,>=3.141.0; extra == "tests"
